ece241_submission_static_analyzer/__init__.py
ece241_submission_static_analyzer/all_rules.py
ece241_submission_static_analyzer/main.py
ece241_submission_static_analyzer/exceptions/__init__.py
ece241_submission_static_analyzer/exceptions/base_exceptions.py
ece241_submission_static_analyzer/exceptions/parsing_exceptions.py
ece241_submission_static_analyzer/rules/__init__.py
ece241_submission_static_analyzer/rules/function_must_return.py
ece241_submission_static_analyzer/rules/no_input_func.py
ece241_submission_static_analyzer/rules/no_root_statements.py
ece241_submission_static_analyzer/rules/require_class.py
ece241_submission_static_analyzer/rules/require_file.py
ece241_submission_static_analyzer/rules/require_function.py
ece241_submission_static_analyzer/rules/rule.py
ece241_submission_static_analyzer/rules/helpers/__init__.py
ece241_submission_static_analyzer/rules/helpers/ast_helper.py
ece241_submission_static_analyzer/rules/helpers/find_classes.py
ece241_submission_static_analyzer/rules/helpers/find_functions.py
ece241_submission_static_analyzer/rules/helpers/find_input_func.py
ece241_submission_static_analyzer/rules/helpers/find_root_statement.py
ece241_submission_static_analyzer/types/__init__.py
ece241_submission_static_analyzer/types/rule_type.py
ece241_submission_static_analyzer/types/severity_type.py
ece241_submission_static_analyzer/types/violation_result.py
ece241_submission_static_analyzer-0.0.5.dist-info/METADATA
ece241_submission_static_analyzer-0.0.5.dist-info/WHEEL
ece241_submission_static_analyzer-0.0.5.dist-info/top_level.txt
ece241_submission_static_analyzer-0.0.5.dist-info/RECORD
